README.md
setup.py
mpl_animation/__init__.py
mpl_animation/anim.py
mpl_animation.egg-info/PKG-INFO
mpl_animation.egg-info/SOURCES.txt
mpl_animation.egg-info/dependency_links.txt
mpl_animation.egg-info/not-zip-safe
mpl_animation.egg-info/requires.txt
mpl_animation.egg-info/top_level.txt