Metadata-Version: 1.1
Name: mpl_animation
Version: 0.1
Summary: A module to create animations in matplotlib using an intuitive declarative syntax
Home-page: https://github.com/braaannigan/mpl_animation
Author: Liam Brannigan
Author-email: braaannigan@gmail.com
License: MIT
Platform: UNKNOWN
Classifier: Programming Language :: Python
Classifier: Programming Language :: Python :: 3
Classifier: Development Status :: 3 - Alpha
Classifier: License :: OSI Approved :: MIT License
Classifier: Topic :: Scientific/Engineering :: Visualization
